bme280spi/__init__.py
bme280spi/__main__.py
bme280spi/helpers.py
bme280spi/main.py
bme280spi/spibyteio.py
bme280spi-0.2.0.dist-info/entry_points.txt
bme280spi-0.2.0.dist-info/LICENSE
bme280spi-0.2.0.dist-info/WHEEL
bme280spi-0.2.0.dist-info/METADATA
bme280spi-0.2.0.dist-info/RECORD
